SimpleProxyManager/SimpleProxyManager.py
SimpleProxyManager/__init__.py
SimpleProxyManager-0.1.2.dist-info/LICENSE.md
SimpleProxyManager-0.1.2.dist-info/METADATA
SimpleProxyManager-0.1.2.dist-info/WHEEL
SimpleProxyManager-0.1.2.dist-info/top_level.txt
SimpleProxyManager-0.1.2.dist-info/RECORD
