Metadata-Version: 2.1
Name: SimpleProxyManager
Version: 0.1.2
Summary: Simple Python multithreaded proxy manager, focused on scrapes
Author-email: "Alessandro G. Magnasco" <amagnasco@gradcenter.cuny.edu>
License: GNU GENERAL PUBLIC LICENSE
Project-URL: Homepage, https://github.com/amagnasco/SimpleProxyManager
Keywords: proxy,scraper,web,http
Classifier: Development Status :: 4 - Beta
Classifier: License :: OSI Approved :: GNU General Public License v3 or later (GPLv3+)
Classifier: Programming Language :: Python
Classifier: Programming Language :: Python :: 3
Requires-Python: >=3.12
License-File: LICENSE.md
Requires-Dist: certifi >=2024.2.2
Requires-Dist: charset-normalizer >=3.3.2
Requires-Dist: idna >=3.7
Requires-Dist: requests >=2.31.0
Requires-Dist: urllib3 >=2.2.1
